datagen/__init__.py
datagen/financial.py
datagen/generator.py
datagen/healthcare.py
datagen/text.py
datagen_python-0.1.0.dist-info/METADATA
datagen_python-0.1.0.dist-info/WHEEL
datagen_python-0.1.0.dist-info/top_level.txt
datagen_python-0.1.0.dist-info/RECORD
