Metadata-Version: 2.1
Name: datagen-python
Version: 0.1.0
Summary: A Python utility for generating synthetic data for various domains
Home-page: 
Author: Connor
Classifier: Development Status :: 3 - Alpha
Classifier: Intended Audience :: Developers
Classifier: Topic :: Software Development :: Libraries :: Python Modules
Classifier: Programming Language :: Python :: 3
Classifier: Programming Language :: Python :: 3.8
Classifier: Programming Language :: Python :: 3.9
Classifier: Programming Language :: Python :: 3.10
Classifier: Programming Language :: Python :: 3.11
Classifier: License :: OSI Approved :: MIT License
Classifier: Operating System :: OS Independent
Requires-Python: >=3.8
Requires-Dist: pandas>=2.0.0
Requires-Dist: numpy>=1.24.0
Requires-Dist: faker>=19.0.0
Requires-Dist: matplotlib>=3.7.0
Requires-Dist: seaborn>=0.12.0
